bogus/__init__.py
bogus/main.py
pdm_github_actions-0.1.0.dist-info/entry_points.txt
pdm_github_actions-0.1.0.dist-info/LICENSE
pdm_github_actions-0.1.0.dist-info/WHEEL
pdm_github_actions-0.1.0.dist-info/METADATA
pdm_github_actions-0.1.0.dist-info/RECORD
