Metadata-Version: 2.1
Name: pdm-github-actions
Version: 0.1.0
Summary: A GitHub Actions demo focused on python
License: CC0 1.0 Universal
Author: JnyJny
Author-email: erik.oshaughnessy@gmail.com
Requires-Python: >=3.9,<4.0
Classifier: License :: Other/Proprietary License
Classifier: Programming Language :: Python :: 3
Classifier: Programming Language :: Python :: 3.9
Requires-Dist: fastapi[webapi] (>=0.65.2,<0.66.0)
Requires-Dist: requests (>=2.25.1,<3.0.0)
Requires-Dist: typer (>=0.3.2,<0.4.0)
Requires-Dist: uvicorn[webapi] (>=0.14.0,<0.15.0)
